validators/__init__.py
validators/_extremes.py
validators/_tld.txt
validators/between.py
validators/card.py
validators/country.py
validators/cron.py
validators/domain.py
validators/email.py
validators/encoding.py
validators/finance.py
validators/hashes.py
validators/hostname.py
validators/iban.py
validators/ip_address.py
validators/length.py
validators/mac_address.py
validators/py.typed
validators/slug.py
validators/uri.py
validators/url.py
validators/utils.py
validators/uuid.py
validators/crypto_addresses/__init__.py
validators/crypto_addresses/btc_address.py
validators/crypto_addresses/eth_address.py
validators/crypto_addresses/trx_address.py
validators/i18n/__init__.py
validators/i18n/es.py
validators/i18n/fi.py
validators/i18n/fr.py
validators/i18n/ind.py
validators-0.32.0.dist-info/LICENSE.txt
validators-0.32.0.dist-info/METADATA
validators-0.32.0.dist-info/WHEEL
validators-0.32.0.dist-info/top_level.txt
validators-0.32.0.dist-info/RECORD
