Metadata-Version: 2.1
Name: validators
Version: 0.32.0
Summary: Python Data Validation for Humans™
Author-email: Konsta Vesterinen <konsta@fastmonkeys.com>
License: MIT
Project-URL: Homepage, https://python-validators.github.io/validators
Project-URL: Documentation, https://yozachar.github.io/pyvalidators
Project-URL: Repository, https://github.com/python-validators/validators
Project-URL: Changelog, https://github.com/python-validators/validators/blob/master/CHANGES.md
Keywords: validation,validator,python-validator
Classifier: Development Status :: 4 - Beta
Classifier: Environment :: Web Environment
Classifier: Intended Audience :: Developers
Classifier: License :: OSI Approved :: MIT License
Classifier: Operating System :: OS Independent
Classifier: Programming Language :: Python
Classifier: Programming Language :: Python :: 3 :: Only
Classifier: Programming Language :: Python :: 3.8
Classifier: Programming Language :: Python :: 3.9
Classifier: Programming Language :: Python :: 3.10
Classifier: Programming Language :: Python :: 3.11
Classifier: Programming Language :: Python :: 3.12
Classifier: Programming Language :: Python :: Implementation :: CPython
Classifier: Topic :: Software Development :: Libraries :: Python Modules
Requires-Python: >=3.8
License-File: LICENSE.txt
Provides-Extra: crypto-eth-addresses
Requires-Dist: eth-hash[pycryptodome]>=0.7.0; extra == "crypto-eth-addresses"
